sm_algo/__init__.py
sm_algo/kmeans.py
sm_algo/linreg.py
sm_algo/logisticreg.py
sm_algo/simplex.py
sm_algo-0.1.2.dist-info/METADATA
sm_algo-0.1.2.dist-info/WHEEL
sm_algo-0.1.2.dist-info/top_level.txt
sm_algo-0.1.2.dist-info/RECORD
